[{"nameRegister":"qwe","surnameRegister":"qwe","nicknameRegister":"qwewqe","emailRegister":"kaka@gmail.com","countryRegister":"ar","passwordRegister":"$2y$10$zJUvpyULEqhytmcWssHyGOI9Euj7ft7.3Md4VY0eYV1QHPeLe3Kiy","avatarRegister":"img_5ce171739d017.png","id":1},{"nameRegister":"qweqweq","surnameRegister":"qweqweqw","nicknameRegister":"qweqweqwe","emailRegister":"qweee@gmail.com","countryRegister":"bo","passwordRegister":"$2y$10$8fmYQFxagN6qli8gDZLRYuP8bb3ie74Gq\/FJdHMBQyV8MiD.HotUm","avatarRegister":"img_5ce173ea40528.jpg","id":2},{"nameRegister":"qweqweqw","surnameRegister":"qweqweqwe","nicknameRegister":"qwewqeqwe","emailRegister":"asfd@gmail.com","countryRegister":"br","passwordRegister":"$2y$10$Ji9UPwI124BqP1eyMRN3euIOQrm7QbG2dRIDiexkf153\/aDvPgEeO","avatarRegister":"img_5ce177bc75c09.jpg","id":3},{"nameRegister":"123","surnameRegister":"123","nicknameRegister":"123","emailRegister":"123@fga.com","countryRegister":"br","passwordRegister":"$2y$10$ezN.PaUMF5YGgrqrvQ9FGuyKMJ.qYZTICj7gMVcwKcvCeHqoiNcta","avatarRegister":"img_5ce17858b84a2.png","id":4}]